{
  "id": "fdb8c931-b1ec-441e-b0ce-75f7a8799189",
  "url": "https://ll.thespacedevs.com/2.2.0/launch/fdb8c931-b1ec-441e-b0ce-75f7a8799189/?format=json",
  "slug": "falcon-9-block-5-starlink-group-6-89",
  "flightclub_url": "https://flightclub.io/result?llId=fdb8c931-b1ec-441e-b0ce-75f7a8799189",
  "r_spacex_api_id": null,
  "name": "Falcon 9 Block 5 | Starlink Group 6-89",
  "status": {
    "id": 3,
    "name": "Launch Successful",
    "abbrev": "Success",
    "description": "The launch vehicle successfully inserted its payload(s) into the target orbit(s)."
  },
  "last_updated": "2025-11-15T08:03:31Z",
  "updates": [
    {
      "id": 12897,
      "profile_image": "https://thespacedevs-prod.nyc3.digitaloceanspaces.com/media/profile_images/cosmic2520penguin_profile_20210817212020.png",
      "comment": "Launch success.",
      "info_url": "https://x.com/SpaceX/status/1989547895800873180",
      "created_by": "Cosmic_Penguin",
      "created_on": "2025-11-15T04:17:00Z"
    },
    {
      "id": 12895,
      "profile_image": "https://thespacedevs-prod.nyc3.digitaloceanspaces.com/media/profile_images/ll2_profile_20230311134739.png",
      "comment": "Unofficial Re-stream by SPACE AFFAIRS has started",
      "info_url": "https://www.youtube.com/watch?v=CmSXEHm4lok",
      "created_by": "LL2",
      "created_on": "2025-11-15T03:09:00Z"
    },
    {
      "id": 12894,
      "profile_image": "https://thespacedevs-prod.nyc3.digitaloceanspaces.com/media/profile_images/cosmic2520penguin_profile_20210817212020.png",
      "comment": "Liftoff.",
      "info_url": "https://x.com/i/broadcasts/1mnxeNjrMvnKX",
      "created_by": "Cosmic_Penguin",
      "created_on": "2025-11-15T03:08:00Z"
    },
    {
      "id": 12887,
      "profile_image": "https://thespacedevs-prod.nyc3.digitaloceanspaces.com/media/profile_images/cosmic2520penguin_profile_20210817212020.png",
      "comment": "New T-0.",
      "info_url": "https://spaceflightnow.com/launch-schedule/",
      "created_by": "Cosmic_Penguin",
      "created_on": "2025-11-14T19:13:00Z"
    },
    {
      "id": 12861,
      "profile_image": "https://thespacedevs-prod.nyc3.digitaloceanspaces.com/media/profile_images/cosmic2520penguin_profile_20210817212020.png",
      "comment": "Updated launch weather, >95% GO.",
      "info_url": "https://45thweathersquadron.nebula.spaceforce.mil/assets/LaunchForecasts/Falcon%209%20Starlink%206-89%20L-2%20Forecast%20-%2014%20Nov%20Launch.pdf",
      "created_by": "Cosmic_Penguin",
      "created_on": "2025-11-12T16:23:00Z"
    },
    {
      "id": 12839,
      "profile_image": "https://thespacedevs-prod.nyc3.digitaloceanspaces.com/media/profile_images/cosmic2520penguin_profile_20210817212020.png",
      "comment": "Now targeting Nov 15 at 03:01 UTC",
      "info_url": "https://www.spacex.com/launches/sl-6-89",
      "created_by": "Cosmic_Penguin",
      "created_on": "2025-11-09T21:54:00Z"
    },
    {
      "id": 12818,
      "profile_image": "https://thespacedevs-prod.nyc3.digitaloceanspaces.com/media/profile_images/cosmic2520penguin_profile_20210817212020.png",
      "comment": "Now targeting Nov 14 at 03:01 UTC",
      "info_url": "https://www.spacex.com/launches/sl-6-89",
      "created_by": "Cosmic_Penguin",
      "created_on": "2025-11-08T23:04:00Z"
    },
    {
      "id": 12751,
      "profile_image": "https://thespacedevs-prod.nyc3.digitaloceanspaces.com/media/profile_images/cosmic2520penguin_profile_20210817212020.png",
      "comment": "Now targeting Nov 13 at 22:35 UTC",
      "info_url": "https://www.spacex.com/launches/sl-6-89",
      "created_by": "Cosmic_Penguin",
      "created_on": "2025-11-03T23:48:00Z"
    },
    {
      "id": 12721,
      "profile_image": "https://thespacedevs-prod.nyc3.digitaloceanspaces.com/media/profile_images/cosmic2520penguin_profile_20210817212020.png",
      "comment": "Added launch.",
      "info_url": "https://www.spacex.com/launches/sl-6-89",
      "created_by": "Cosmic_Penguin",
      "created_on": "2025-10-30T21:23:00Z"
    }
  ],
  "net": "2025-11-15T03:08:10Z",
  "net_precision": {
    "id": 0,
    "name": "Second",
    "abbrev": "SEC",
    "description": "The T-0 is accurate to the second."
  },
  "window_end": "2025-11-15T07:01:00Z",
  "window_start": "2025-11-15T03:01:00Z",
  "probability": 99,
  "weather_concerns": null,
  "holdreason": "",
  "failreason": "",
  "hashtag": null,
  "launch_service_provider": {
    "id": 121,
    "url": "https://ll.thespacedevs.com/2.2.0/agencies/121/?format=json",
    "name": "SpaceX",
    "featured": true,
    "type": "Commercial",
    "country_code": "USA",
    "abbrev": "SpX",
    "description": "Space Exploration Technologies Corp., known as SpaceX, is an American aerospace manufacturer and space transport services company headquartered in Hawthorne, California. It was founded in 2002 by entrepreneur Elon Musk with the goal of reducing space transportation costs and enabling the colonization of Mars. SpaceX operates from many pads, on the East Coast of the US they operate from SLC-40 at Cape Canaveral Space Force Station and historic LC-39A at Kennedy Space Center. They also operate from SLC-4E at Vandenberg Space Force Base, California, usually for polar launches. Another launch site is being developed at Boca Chica, Texas.",
    "administrator": "CEO: Elon Musk",
    "founding_year": "2002",
    "launchers": "Falcon | Starship",
    "spacecraft": "Dragon",
    "launch_library_url": null,
    "total_launch_count": 601,
    "consecutive_successful_launches": 85,
    "successful_launches": 585,
    "failed_launches": 15,
    "pending_launches": 116,
    "consecutive_successful_landings": 85,
    "successful_landings": 546,
    "failed_landings": 27,
    "attempted_landings": 572,
    "info_url": "https://www.spacex.com/",
    "wiki_url": "https://en.wikipedia.org/wiki/SpaceX",
    "logo_url": "https://thespacedevs-prod.nyc3.digitaloceanspaces.com/media/images/spacex_logo_20220826094919.png",
    "image_url": "https://thespacedevs-prod.nyc3.digitaloceanspaces.com/media/images/spacex_image_20190207032501.jpeg",
    "nation_url": "https://thespacedevs-prod.nyc3.digitaloceanspaces.com/media/images/spacex_nation_20230531064544.jpg"
  },
  "rocket": {
    "id": 8786,
    "configuration": {
      "id": 164,
      "url": "https://ll.thespacedevs.com/2.2.0/config/launcher/164/?format=json",
      "name": "Falcon 9",
      "active": true,
      "reusable": true,
      "description": "Falcon 9 is a two-stage rocket designed and manufactured by SpaceX for the reliable and safe transport of satellites and the Dragon spacecraft into orbit. The Block 5 variant is the fifth major interval aimed at improving upon the ability for rapid reusability.",
      "family": "Falcon",
      "full_name": "Falcon 9 Block 5",
      "manufacturer": {
        "id": 121,
        "url": "https://ll.thespacedevs.com/2.2.0/agencies/121/?format=json",
        "name": "SpaceX",
        "featured": true,
        "type": "Commercial",
        "country_code": "USA",
        "abbrev": "SpX",
        "description": "Space Exploration Technologies Corp., known as SpaceX, is an American aerospace manufacturer and space transport services company headquartered in Hawthorne, California. It was founded in 2002 by entrepreneur Elon Musk with the goal of reducing space transportation costs and enabling the colonization of Mars. SpaceX operates from many pads, on the East Coast of the US they operate from SLC-40 at Cape Canaveral Space Force Station and historic LC-39A at Kennedy Space Center. They also operate from SLC-4E at Vandenberg Space Force Base, California, usually for polar launches. Another launch site is being developed at Boca Chica, Texas.",
        "administrator": "CEO: Elon Musk",
        "founding_year": "2002",
        "launchers": "Falcon | Starship",
        "spacecraft": "Dragon",
        "launch_library_url": null,
        "total_launch_count": 601,
        "consecutive_successful_launches": 85,
        "successful_launches": 585,
        "failed_launches": 15,
        "pending_launches": 116,
        "consecutive_successful_landings": 85,
        "successful_landings": 546,
        "failed_landings": 27,
        "attempted_landings": 572,
        "info_url": "https://www.spacex.com/",
        "wiki_url": "https://en.wikipedia.org/wiki/SpaceX",
        "logo_url": "https://thespacedevs-prod.nyc3.digitaloceanspaces.com/media/images/spacex_logo_20220826094919.png",
        "image_url": "https://thespacedevs-prod.nyc3.digitaloceanspaces.com/media/images/spacex_image_20190207032501.jpeg",
        "nation_url": "https://thespacedevs-prod.nyc3.digitaloceanspaces.com/media/images/spacex_nation_20230531064544.jpg"
      },
      "program": [
        {
          "id": 11,
          "url": "https://ll.thespacedevs.com/2.2.0/program/11/?format=json",
          "name": "Commercial Resupply Services",
          "description": "Commercial Resupply Services (CRS) are a series of flights awarded by NASA for the delivery of cargo and supplies to the International Space Station.The first CRS contracts were signed in 2008 and awarded $1.6 billion to SpaceX for twelve cargo Dragon and $1.9 billion to Orbital Sciences for eight Cygnus flights, covering deliveries to 2016. The Falcon 9 and Antares rockets were also developed under the CRS program to deliver cargo spacecraft to the ISS.",
          "agencies": [
            {
              "id": 44,
              "url": "https://ll.thespacedevs.com/2.2.0/agencies/44/?format=json",
              "name": "National Aeronautics and Space Administration",
              "type": "Government"
            },
            {
              "id": 257,
              "url": "https://ll.thespacedevs.com/2.2.0/agencies/257/?format=json",
              "name": "Northrop Grumman Space Systems",
              "type": "Commercial"
            },
            {
              "id": 1020,
              "url": "https://ll.thespacedevs.com/2.2.0/agencies/1020/?format=json",
              "name": "Sierra Nevada Corporation",
              "type": "Commercial"
            },
            {
              "id": 121,
              "url": "https://ll.thespacedevs.com/2.2.0/agencies/121/?format=json",
              "name": "SpaceX",
              "type": "Commercial"
            }
          ],
          "image_url": "https://thespacedevs-prod.nyc3.digitaloceanspaces.com/media/images/commercial2520_program_20201129212219.png",
          "start_date": "2008-12-23T00:00:00Z",
          "end_date": null,
          "info_url": null,
          "wiki_url": "https://en.wikipedia.org/wiki/Commercial_Resupply_Services#Commercial_Resupply_Services",
          "mission_patches": [],
          "type": {
            "id": 2,
            "name": "Human Spaceflight"
          }
        },
        {
          "id": 5,
          "url": "https://ll.thespacedevs.com/2.2.0/program/5/?format=json",
          "name": "Commercial Crew Program",
          "description": "The Commercial Crew Program (CCP) is a human spaceflight program operated by NASA, in association with American aerospace manufacturers Boeing and SpaceX. The program conducts rotations between the expeditions of the International Space Station program, transporting crews to and from the International Space Station (ISS) aboard Boeing Starliner and SpaceX Crew Dragon capsules, in the first crewed orbital spaceflights operated by private companies.",
          "agencies": [
            {
              "id": 80,
              "url": "https://ll.thespacedevs.com/2.2.0/agencies/80/?format=json",
              "name": "Boeing",
              "type": "Commercial"
            },
            {
              "id": 44,
              "url": "https://ll.thespacedevs.com/2.2.0/agencies/44/?format=json",
              "name": "National Aeronautics and Space Administration",
              "type": "Government"
            },
            {
              "id": 121,
              "url": "https://ll.thespacedevs.com/2.2.0/agencies/121/?format=json",
              "name": "SpaceX",
              "type": "Commercial"
            }
          ],
          "image_url": "https://thespacedevs-prod.nyc3.digitaloceanspaces.com/media/images/commercial2520_program_20200820201209.png",
          "start_date": "2011-04-18T00:00:00Z",
          "end_date": null,
          "info_url": "https://www.nasa.gov/exploration/commercial/crew/index.html",
          "wiki_url": "https://en.wikipedia.org/wiki/Commercial_Crew_Program",
          "mission_patches": [],
          "type": {
            "id": 2,
            "name": "Human Spaceflight"
          }
        }
      ],
      "variant": "Block 5",
      "alias": "",
      "min_stage": 2,
      "max_stage": 2,
      "length": 70,
      "diameter": 3.65,
      "maiden_flight": "2018-05-11",
      "launch_cost": "52000000",
      "launch_mass": 549,
      "leo_capacity": 22800,
      "gto_capacity": 8300,
      "to_thrust": 7607,
      "apogee": 200,
      "vehicle_range": null,
      "image_url": "https://thespacedevs-prod.nyc3.digitaloceanspaces.com/media/images/falcon_9_image_20230807133459.jpeg",
      "info_url": "https://www.spacex.com/vehicles/falcon-9/",
      "wiki_url": "https://en.wikipedia.org/wiki/Falcon_9",
      "total_launch_count": 508,
      "consecutive_successful_launches": 209,
      "successful_launches": 506,
      "failed_launches": 1,
      "pending_launches": 98,
      "attempted_landings": 499,
      "successful_landings": 494,
      "failed_landings": 5,
      "consecutive_successful_landings": 194
    },
    "launcher_stage": [
      {
        "id": 838,
        "type": "Core",
        "reused": true,
        "launcher_flight_number": 8,
        "launcher": {
          "id": 192,
          "url": "https://ll.thespacedevs.com/2.2.0/launcher/192/?format=json",
          "details": "Falcon 9 booster debuting on Starlink Group 12-13.",
          "flight_proven": true,
          "serial_number": "B1092",
          "status": "active",
          "image_url": "https://thespacedevs-prod.nyc3.digitaloceanspaces.com/media/images/b1092_landing_a_image_20250325084800.jpg",
          "successful_landings": 8,
          "attempted_landings": 8,
          "flights": 8,
          "last_launch_date": "2025-11-15T03:08:10Z",
          "first_launch_date": "2025-02-27T03:34:20Z"
        },
        "landing": {
          "id": 1733,
          "attempt": true,
          "success": true,
          "description": "The Falcon 9 first stage B1092 has landed on ASDS ASOG after its 8th flight.",
          "downrange_distance": 600,
          "location": {
            "id": 17,
            "name": "A Shortfall of Gravitas",
            "abbrev": "ASOG",
            "description": "The fourth ASDS barge, A Shortfall of Gravitas (ASOG) is currently used to recover Falcon 9 and Heavy boosters in the Altantic Ocean.",
            "location": null,
            "successful_landings": 132
          },
          "type": {
            "id": 1,
            "name": "Autonomous Spaceport Drone Ship",
            "abbrev": "ASDS",
            "description": "An autonomous spaceport drone ship (ASDS) is an ocean-going vessel derived from a deck barge, outfitted with station-keeping engines and a large landing platform. Construction of such ships was commissioned by aerospace company SpaceX to allow for recovery of rocket first-stages at sea for high-velocity missions which do not carry enough fuel to return to the launch site after lofting spacecraft onto an orbital trajectory."
          }
        },
        "previous_flight_date": "2025-09-18T09:30:00Z",
        "turn_around_time_days": 57,
        "previous_flight": {
          "id": "09678f8e-d3e5-4e26-87c1-d9b9141c1f61",
          "name": "Falcon 9 Block 5 | Starlink Group 10-61"
        }
      }
    ],
    "spacecraft_stage": null
  },
  "mission": {
    "id": 7377,
    "name": "Starlink Group 6-89",
    "description": "A batch of 29 satellites for the Starlink mega-constellation - SpaceX's project for space-based Internet communication system.",
    "launch_designator": null,
    "type": "Communications",
    "orbit": {
      "id": 8,
      "name": "Low Earth Orbit",
      "abbrev": "LEO"
    },
    "agencies": [
      {
        "id": 121,
        "url": "https://ll.thespacedevs.com/2.2.0/agencies/121/?format=json",
        "name": "SpaceX",
        "featured": true,
        "type": "Commercial",
        "country_code": "USA",
        "abbrev": "SpX",
        "description": "Space Exploration Technologies Corp., known as SpaceX, is an American aerospace manufacturer and space transport services company headquartered in Hawthorne, California. It was founded in 2002 by entrepreneur Elon Musk with the goal of reducing space transportation costs and enabling the colonization of Mars. SpaceX operates from many pads, on the East Coast of the US they operate from SLC-40 at Cape Canaveral Space Force Station and historic LC-39A at Kennedy Space Center. They also operate from SLC-4E at Vandenberg Space Force Base, California, usually for polar launches. Another launch site is being developed at Boca Chica, Texas.",
        "administrator": "CEO: Elon Musk",
        "founding_year": "2002",
        "launchers": "Falcon | Starship",
        "spacecraft": "Dragon",
        "launch_library_url": null,
        "total_launch_count": 601,
        "consecutive_successful_launches": 85,
        "successful_launches": 585,
        "failed_launches": 15,
        "pending_launches": 116,
        "consecutive_successful_landings": 85,
        "successful_landings": 546,
        "failed_landings": 27,
        "attempted_landings": 572,
        "info_url": "https://www.spacex.com/",
        "wiki_url": "https://en.wikipedia.org/wiki/SpaceX",
        "logo_url": "https://thespacedevs-prod.nyc3.digitaloceanspaces.com/media/images/spacex_logo_20220826094919.png",
        "image_url": "https://thespacedevs-prod.nyc3.digitaloceanspaces.com/media/images/spacex_image_20190207032501.jpeg",
        "nation_url": "https://thespacedevs-prod.nyc3.digitaloceanspaces.com/media/images/spacex_nation_20230531064544.jpg"
      }
    ],
    "info_urls": [],
    "vid_urls": []
  },
  "pad": {
    "id": 87,
    "url": "https://ll.thespacedevs.com/2.2.0/pad/87/?format=json",
    "agency_id": 121,
    "name": "Launch Complex 39A",
    "description": "",
    "info_url": null,
    "wiki_url": "https://en.wikipedia.org/wiki/Kennedy_Space_Center_Launch_Complex_39#Launch_Pad_39A",
    "map_url": "https://www.google.com/maps?q=28.60822681,-80.60428186",
    "latitude": "28.60822681",
    "longitude": "-80.60428186",
    "location": {
      "id": 27,
      "url": "https://ll.thespacedevs.com/2.2.0/location/27/?format=json",
      "name": "Kennedy Space Center, FL, USA",
      "country_code": "USA",
      "description": "The John F. Kennedy Space Center, located on Merritt Island, Florida, is one of NASA's ten field centers. Since 1968, KSC has been NASA's primary launch center of American spaceflight, research, and technology. Launch operations for the Apollo, Skylab and Space Shuttle programs were carried out from Kennedy Space Center Launch Complex 39 and managed by KSC. Located on the east coast of Florida, KSC is adjacent to Cape Canaveral Space Force Station (CCSFS).",
      "map_image": "https://thespacedevs-prod.nyc3.digitaloceanspaces.com/media/map_images/location_27_20200803142447.jpg",
      "timezone_name": "America/New_York",
      "total_launch_count": 275,
      "total_landing_count": 0
    },
    "country_code": "USA",
    "map_image": "https://thespacedevs-prod.nyc3.digitaloceanspaces.com/media/map_images/pad_87_20200803143537.jpg",
    "total_launch_count": 217,
    "orbital_launch_attempt_count": 216
  },
  "infoURLs": [
    {
      "priority": 10,
      "source": "spacex.com",
      "title": "SpaceX",
      "description": "SpaceX designs, manufactures and launches advanced rockets and spacecraft. The company was founded in 2002 to revolutionize space technology, with the ultimate goal of enabling people to live on other planets.",
      "feature_image": null,
      "url": "https://www.spacex.com/launches/sl-6-89",
      "type": {
        "id": 1,
        "name": "Official Page"
      },
      "language": {
        "id": 1,
        "name": "English",
        "code": "en"
      }
    }
  ],
  "vidURLs": [
    {
      "priority": 7,
      "source": "",
      "publisher": "The Space Devs",
      "title": "SpaceX Starlink Group 6-89",
      "description": "On Saturday November 15, 2025, SpaceX launched the Starlink Group 6-89 mission with a Falcon 9 Block 5 from Launch Complex 39A at Kennedy Space Center, FL, USA.\n\nDescription generated from the Launch ...",
      "feature_image": "https://i.ytimg.com/vi/RJBqvdktfAs/hqdefault.jpg",
      "url": "https://www.youtube.com/watch?v=RJBqvdktfAs",
      "type": {
        "id": 4,
        "name": "Unofficial Re-stream"
      },
      "language": {
        "id": 1,
        "name": "English",
        "code": "en"
      },
      "start_time": null,
      "end_time": null
    },
    {
      "priority": 8,
      "source": null,
      "publisher": "Spaceflight Now",
      "title": "Watch Live: SpaceX launches Starlink satellites on Falcon 9 rocket from NASA's Kennedy Space Center",
      "description": "Watch live coverage as SpaceX launches a Falcon 9 rocket with 29 satellites for the company's Starlink internet service.  Liftoff from Launch Complex 39A is scheduled at 10:08 p.m. EST (0308 UTC) . Th...",
      "feature_image": "https://i.ytimg.com/vi/zPLt9OuWeyg/maxresdefault.jpg",
      "url": "https://www.youtube.com/watch?v=zPLt9OuWeyg",
      "type": {
        "id": 3,
        "name": "Unofficial Webcast"
      },
      "language": {
        "id": 1,
        "name": "English",
        "code": "en"
      },
      "start_time": "2025-11-15T02:09:03Z",
      "end_time": "2025-11-15T03:38:21Z"
    },
    {
      "priority": 9,
      "source": "youtube.com",
      "publisher": "NASASpaceflight",
      "title": "SpaceX Falcon 9 Cape Doubleheader with Starlinks 6-89 and 6-85",
      "description": "Potential doubleheader of two SpaceX Falcon 9's launching in the same window from 39A and SLC-40, both carrying 29 Starlink v2-mini satellites for their second-generation high-speed low earth orbit in...",
      "feature_image": "https://i.ytimg.com/vi/HsJcGy3KhoM/maxresdefault.jpg",
      "url": "https://www.youtube.com/watch?v=HsJcGy3KhoM",
      "type": {
        "id": 3,
        "name": "Unofficial Webcast"
      },
      "language": {
        "id": 1,
        "name": "English",
        "code": "en"
      },
      "start_time": "2025-11-15T02:15:21Z",
      "end_time": "2025-11-15T07:15:27Z"
    },
    {
      "priority": 10,
      "source": "x.com",
      "publisher": "X",
      "title": "Livestream on X",
      "description": "Livestream on X",
      "feature_image": null,
      "url": "https://x.com/i/broadcasts/1mnxeNjrMvnKX",
      "type": {
        "id": 1,
        "name": "Official Webcast"
      },
      "language": {
        "id": 1,
        "name": "English",
        "code": "en"
      },
      "start_time": null,
      "end_time": null
    }
  ],
  "webcast_live": false,
  "timeline": [
    {
      "type": {
        "id": 11,
        "abbrev": "Max-Q",
        "description": "Maximum dynamic pressure"
      },
      "relative_time": "PT1M12S"
    },
    {
      "type": {
        "id": 12,
        "abbrev": "MECO",
        "description": "Cut-off of the main engine"
      },
      "relative_time": "PT2M27S"
    },
    {
      "type": {
        "id": 13,
        "abbrev": "Stage 2 Separation",
        "description": "Separation of the second stage from the first"
      },
      "relative_time": "PT2M31S"
    },
    {
      "type": {
        "id": 14,
        "abbrev": "SES-1",
        "description": "First start of the second engine"
      },
      "relative_time": "PT2M39S"
    },
    {
      "type": {
        "id": 15,
        "abbrev": "Fairing Separation",
        "description": "Separation of the payload fairing"
      },
      "relative_time": "PT2M53S"
    },
    {
      "type": {
        "id": 16,
        "abbrev": "Entry Burn Startup",
        "description": "Start of the atmospheric entry burn"
      },
      "relative_time": "PT6M9S"
    },
    {
      "type": {
        "id": 17,
        "abbrev": "Entry Burn Shutdown",
        "description": "End of the atmospheric entry burn"
      },
      "relative_time": "PT6M35S"
    },
    {
      "type": {
        "id": 18,
        "abbrev": "Stage 1 Landing Burn",
        "description": "Start of the first stage landing burn"
      },
      "relative_time": "PT8M"
    },
    {
      "type": {
        "id": 19,
        "abbrev": "Stage 1 Landing",
        "description": "Landing of the first stage"
      },
      "relative_time": "PT8M22S"
    },
    {
      "type": {
        "id": 20,
        "abbrev": "SECO-1",
        "description": "First cut-off of the second engine"
      },
      "relative_time": "PT8M42S"
    },
    {
      "type": {
        "id": 21,
        "abbrev": "SES-2",
        "description": "Second start of the second engine"
      },
      "relative_time": "PT53M57S"
    },
    {
      "type": {
        "id": 22,
        "abbrev": "SECO-2",
        "description": "Second cut-off of the second engine"
      },
      "relative_time": "PT53M58S"
    },
    {
      "type": {
        "id": 23,
        "abbrev": "Starlink Deployment",
        "description": "Deployment of the Starlink stack from the rocket"
      },
      "relative_time": "PT1H5M5S"
    }
  ],
  "image": "https://thespacedevs-prod.nyc3.digitaloceanspaces.com/media/images/falcon2520925_image_20221009234147.png",
  "infographic": null,
  "program": [
    {
      "id": 25,
      "url": "https://ll.thespacedevs.com/2.2.0/program/25/?format=json",
      "name": "Starlink",
      "description": "Starlink is a satellite internet constellation operated by American aerospace company SpaceX",
      "agencies": [
        {
          "id": 121,
          "url": "https://ll.thespacedevs.com/2.2.0/agencies/121/?format=json",
          "name": "SpaceX",
          "type": "Commercial"
        }
      ],
      "image_url": "https://thespacedevs-prod.nyc3.digitaloceanspaces.com/media/images/starlink_program_20231228154508.jpeg",
      "start_date": "2018-02-22T14:17:00Z",
      "end_date": null,
      "info_url": "https://starlink.com",
      "wiki_url": "https://en.wikipedia.org/wiki/Starlink",
      "mission_patches": [
        {
          "id": 7,
          "name": "Space X Starlink Mission Patch",
          "priority": 10,
          "image_url": "https://thespacedevs-prod.nyc3.digitaloceanspaces.com/media/mission_patch_images/space2520x252_mission_patch_20221011205756.png",
          "agency": {
            "id": 121,
            "url": "https://ll.thespacedevs.com/2.2.0/agencies/121/?format=json",
            "name": "SpaceX",
            "type": "Commercial"
          }
        }
      ],
      "type": {
        "id": 3,
        "name": "Communication Constellation"
      }
    }
  ],
  "orbital_launch_attempt_count": 7118,
  "location_launch_attempt_count": 275,
  "pad_launch_attempt_count": 217,
  "agency_launch_attempt_count": 599,
  "orbital_launch_attempt_count_year": 269,
  "location_launch_attempt_count_year": 23,
  "pad_launch_attempt_count_year": 23,
  "agency_launch_attempt_count_year": 150,
  "pad_turnaround": "P5DT18H58M",
  "mission_patches": [
    {
      "id": 7,
      "name": "Space X Starlink Mission Patch",
      "priority": 10,
      "image_url": "https://thespacedevs-prod.nyc3.digitaloceanspaces.com/media/mission_patch_images/space2520x252_mission_patch_20221011205756.png",
      "agency": {
        "id": 121,
        "url": "https://ll.thespacedevs.com/2.2.0/agencies/121/?format=json",
        "name": "SpaceX",
        "type": "Commercial"
      }
    }
  ],
  "type": "detailed"
}