{
  "count": 194,
  "next": "https://ll.thespacedevs.com/2.2.0/launch/?format=json&limit=1&lsp__ids=121&mode=detailed&net__lt=2022-09-24T06%3A11%3A17Z&offset=1&ordering=-net",
  "previous": null,
  "results": [
    {
      "id": "9ba04064-c329-40bf-b477-ff468d7d8058",
      "url": "https://ll.thespacedevs.com/2.2.0/launch/9ba04064-c329-40bf-b477-ff468d7d8058/?format=json",
      "slug": "falcon-9-block-5-starlink-group-4-34",
      "flightclub_url": "https://flightclub.io/result?llId=9ba04064-c329-40bf-b477-ff468d7d8058",
      "r_spacex_api_id": null,
      "name": "Falcon 9 Block 5 | Starlink Group 4-34",
      "status": {
        "id": 3,
        "name": "Launch Successful",
        "abbrev": "Success",
        "description": "The launch vehicle successfully inserted its payload(s) into the target orbit(s)."
      },
      "last_updated": "2023-06-14T17:40:29Z",
      "updates": [
        {
          "id": 2438,
          "profile_image": "https://spacelaunchnow-prod-east.nyc3.digitaloceanspaces.com/media/profile_images/swgustav_profile_20210218062738.jpg",
          "comment": "Successful deployment of 54 Starlink satellites",
          "info_url": "https://twitter.com/SpaceX/status/1571659346437603334",
          "created_by": "SwGustav",
          "created_on": "2022-09-19T00:37:23Z"
        },
        {
          "id": 2437,
          "profile_image": "https://spacelaunchnow-prod-east.nyc3.digitaloceanspaces.com/media/profile_images/swgustav_profile_20210218062738.jpg",
          "comment": "Liftoff",
          "info_url": "https://www.youtube.com/watch?v=ZlQHF_yBkMQ",
          "created_by": "SwGustav",
          "created_on": "2022-09-19T00:19:09Z"
        },
        {
          "id": 2436,
          "profile_image": "https://spacelaunchnow-prod-east.nyc3.digitaloceanspaces.com/media/profile_images/swgustav_profile_20210218062738.jpg",
          "comment": "Coverage is live",
          "info_url": "https://www.youtube.com/watch?v=ZlQHF_yBkMQ",
          "created_by": "SwGustav",
          "created_on": "2022-09-19T00:13:31Z"
        },
        {
          "id": 2435,
          "profile_image": "https://spacelaunchnow-prod-east.nyc3.digitaloceanspaces.com/media/profile_images/swgustav_profile_20210218062738.jpg",
          "comment": "Updating weather",
          "info_url": "https://www.patrick.spaceforce.mil/Portals/14/Weather/Falcon%209%20Starlink%204-34%20L-1%20Forecast%20-%2018%20Sept%20Launch.pdf",
          "created_by": "SwGustav",
          "created_on": "2022-09-19T00:13:31Z"
        },
        {
          "id": 2434,
          "profile_image": "https://spacelaunchnow-prod-east.nyc3.digitaloceanspaces.com/media/profile_images/swgustav_profile_20210218062738.jpg",
          "comment": "Updating weather",
          "info_url": "https://www.patrick.spaceforce.mil/Portals/14/Weather/Falcon%209%20Starlink%204-34%20L-1%20Forecast%20-%2018%20Sept%20Launch.pdf",
          "created_by": "SwGustav",
          "created_on": "2022-09-18T23:51:26Z"
        },
        {
          "id": 2432,
          "profile_image": "https://spacelaunchnow-prod-east.nyc3.digitaloceanspaces.com/media/profile_images/swgustav_profile_20210218062738.jpg",
          "comment": "24 hour delay",
          "info_url": "https://twitter.com/SpaceX/status/1571264161455243275",
          "created_by": "SwGustav",
          "created_on": "2022-09-17T22:29:39Z"
        },
        {
          "id": 2428,
          "profile_image": "https://spacelaunchnow-prod-east.nyc3.digitaloceanspaces.com/media/profile_images/arnaud2520muller_profile_20230607144351.jpg",
          "comment": "Weather 20%",
          "info_url": "https://www.patrick.spaceforce.mil/Portals/14/Weather/Falcon%209%20Starlink%204-34%20L-1%20Forecast%20-%2017%20Sept%20Launch.pdf",
          "created_by": "Nosu",
          "created_on": "2022-09-17T04:18:24Z"
        },
        {
          "id": 2427,
          "profile_image": "https://spacelaunchnow-prod-east.nyc3.digitaloceanspaces.com/media/profile_images/swgustav_profile_20210218062738.jpg",
          "comment": "Scrub and 24 hours recycle due to weather",
          "info_url": "https://twitter.com/SpaceX/status/1570944576147582976",
          "created_by": "SwGustav",
          "created_on": "2022-09-17T01:17:10Z"
        },
        {
          "id": 2426,
          "profile_image": "https://spacelaunchnow-prod-east.nyc3.digitaloceanspaces.com/media/profile_images/swgustav_profile_20210218062738.jpg",
          "comment": "Coverage is live",
          "info_url": "https://www.youtube.com/watch?v=f3TWiIjDVSs",
          "created_by": "SwGustav",
          "created_on": "2022-09-17T01:10:49Z"
        },
        {
          "id": 2425,
          "profile_image": "https://spacelaunchnow-prod-east.nyc3.digitaloceanspaces.com/media/profile_images/jay2520keegan_profile_20221218022555.jpg",
          "comment": "Now targeting 01:15 UTC",
          "info_url": "https://twitter.com/spacex/status/1570928136203927552",
          "created_by": "Jay",
          "created_on": "2022-09-17T00:13:12Z"
        },
        {
          "id": 2424,
          "profile_image": "https://spacelaunchnow-prod-east.nyc3.digitaloceanspaces.com/media/profile_images/cosmic2520penguin_profile_20210817212020.png",
          "comment": "New T-0",
          "info_url": "https://twitter.com/spacex/status/1570916372796047361",
          "created_by": "Cosmic_Penguin",
          "created_on": "2022-09-16T23:25:32Z"
        },
        {
          "id": 2421,
          "profile_image": "https://spacelaunchnow-prod-east.nyc3.digitaloceanspaces.com/media/profile_images/swgustav_profile_20210218062738.jpg",
          "comment": "Scrub, 24 hour delay due to weather",
          "info_url": "https://twitter.com/SpaceX/status/1570585787762380801",
          "created_by": "SwGustav",
          "created_on": "2022-09-16T01:30:56Z"
        },
        {
          "id": 2420,
          "profile_image": "https://spacelaunchnow-prod-east.nyc3.digitaloceanspaces.com/media/profile_images/swgustav_profile_20210218062738.jpg",
          "comment": "Coverage live",
          "info_url": "https://www.youtube.com/watch?v=JzWSYJBSAl4",
          "created_by": "SwGustav",
          "created_on": "2022-09-16T01:22:32Z"
        },
        {
          "id": 2419,
          "profile_image": "https://spacelaunchnow-prod-east.nyc3.digitaloceanspaces.com/media/profile_images/swgustav_profile_20210218062738.jpg",
          "comment": "Updating weather",
          "info_url": "https://twitter.com/spacex/status/1570577586287439872",
          "created_by": "SwGustav",
          "created_on": "2022-09-16T01:00:39Z"
        },
        {
          "id": 2412,
          "profile_image": "https://spacelaunchnow-prod-east.nyc3.digitaloceanspaces.com/media/profile_images/arnaud2520muller_profile_20230607144351.jpg",
          "comment": "Weather 40%",
          "info_url": "https://www.patrick.spaceforce.mil/Portals/14/Weather/Falcon%209%20Starlink%204-34%20L-1%20Forecast%20-%2015%20Sept%20Launch.pdf",
          "created_by": "Nosu",
          "created_on": "2022-09-15T08:32:09Z"
        },
        {
          "id": 2408,
          "profile_image": "https://spacelaunchnow-prod-east.nyc3.digitaloceanspaces.com/media/profile_images/cosmic2520penguin_profile_20210817212020.png",
          "comment": "24 hours slip due to weather",
          "info_url": "https://twitter.com/spacex/status/1570209338928820225",
          "created_by": "Cosmic_Penguin",
          "created_on": "2022-09-15T00:36:46Z"
        },
        {
          "id": 2405,
          "profile_image": "https://spacelaunchnow-prod-east.nyc3.digitaloceanspaces.com/media/profile_images/swgustav_profile_20210218062738.jpg",
          "comment": "Updating weather",
          "info_url": "https://www.patrick.spaceforce.mil/Portals/14/Weather/Falcon%209%20Starlink%204-34%20L-1%20Forecast%20-%2014%20Sept%20Launch.pdf",
          "created_by": "SwGustav",
          "created_on": "2022-09-14T23:01:51Z"
        },
        {
          "id": 2392,
          "profile_image": "https://spacelaunchnow-prod-east.nyc3.digitaloceanspaces.com/media/profile_images/cosmic2520penguin_profile_20210817212020.png",
          "comment": "24 hours slip due to weather",
          "info_url": "https://twitter.com/spacex/status/1569862210167443456?s=46&t=3kStM6vMnuQQuurFMDRLEQ",
          "created_by": "Cosmic_Penguin",
          "created_on": "2022-09-14T01:37:20Z"
        },
        {
          "id": 2388,
          "profile_image": "https://spacelaunchnow-prod-east.nyc3.digitaloceanspaces.com/media/profile_images/arnaud2520muller_profile_20230607144351.jpg",
          "comment": "Weather 50%",
          "info_url": "https://www.patrick.spaceforce.mil/Portals/14/Weather/Falcon%209%20Starlink%204-34%20L-0%20Forecast%20-%2013%20Sept%20Launch.pdf",
          "created_by": "Nosu",
          "created_on": "2022-09-13T12:43:21Z"
        },
        {
          "id": 2384,
          "profile_image": "https://spacelaunchnow-prod-east.nyc3.digitaloceanspaces.com/media/profile_images/arnaud2520muller_profile_20230607144351.jpg",
          "comment": "Weather 60%",
          "info_url": "https://www.patrick.spaceforce.mil/Portals/14/Weather/Falcon%209%20Starlink%204-34%20L-1%20Forecast%20-%2013%20Sept%20Launch.pdf",
          "created_by": "Nosu",
          "created_on": "2022-09-12T15:02:21Z"
        },
        {
          "id": 2373,
          "profile_image": "https://spacelaunchnow-prod-east.nyc3.digitaloceanspaces.com/media/profile_images/cosmic2520penguin_profile_20210817212020.png",
          "comment": "Go for launch",
          "info_url": "https://twitter.com/spacex/status/1568956790934470656?s=46&t=U6GqT1mTMY5dpmzTPpB6iQ",
          "created_by": "Cosmic_Penguin",
          "created_on": "2022-09-11T13:38:13Z"
        },
        {
          "id": 2372,
          "profile_image": "https://spacelaunchnow-prod-east.nyc3.digitaloceanspaces.com/media/profile_images/arnaud2520muller_profile_20230607144351.jpg",
          "comment": "Weather 70%",
          "info_url": "https://www.patrick.spaceforce.mil/Portals/14/Weather/Falcon%209%20Starlink%204-34%20L-2%20Forecast%20-%2013%20Sept%20Launch.pdf",
          "created_by": "Nosu",
          "created_on": "2022-09-11T13:35:02Z"
        },
        {
          "id": 2371,
          "profile_image": "https://spacelaunchnow-prod-east.nyc3.digitaloceanspaces.com/media/profile_images/cosmic2520penguin_profile_20210817212020.png",
          "comment": "Updated T-0",
          "info_url": "https://forum.nasaspaceflight.com/index.php?topic=56921.msg2406720#msg2406720",
          "created_by": "Cosmic_Penguin",
          "created_on": "2022-09-11T13:33:47Z"
        },
        {
          "id": 2369,
          "profile_image": "https://spacelaunchnow-prod-east.nyc3.digitaloceanspaces.com/media/profile_images/cosmic2520penguin_profile_20210817212020.png",
          "comment": "NET September 14 UTC",
          "info_url": "https://forum.nasaspaceflight.com/index.php?topic=56921.msg2406627#msg2406627",
          "created_by": "Cosmic_Penguin",
          "created_on": "2022-09-11T02:28:13Z"
        },
        {
          "id": 2365,
          "profile_image": "https://spacelaunchnow-prod-east.nyc3.digitaloceanspaces.com/media/profile_images/arnaud2520muller_profile_20230607144351.jpg",
          "comment": "Weather 80%",
          "info_url": "https://www.patrick.spaceforce.mil/Portals/14/Weather/Falcon%209%20Starlink%204-34%20L-1%20Forecast%20-%2011%20Sept%20Launch.pdf",
          "created_by": "Nosu",
          "created_on": "2022-09-10T12:50:06Z"
        },
        {
          "id": 2357,
          "profile_image": "https://spacelaunchnow-prod-east.nyc3.digitaloceanspaces.com/media/profile_images/arnaud2520muller_profile_20230607144351.jpg",
          "comment": "Adjusting T-0 and setting Weather 70%",
          "info_url": "https://www.patrick.spaceforce.mil/Portals/14/Weather/Falcon%209%20Starlink%204-34%20L-3%20Forecast%20-%2011%20Sept%20Launch.pdf",
          "created_by": "Nosu",
          "created_on": "2022-09-08T16:05:57Z"
        },
        {
          "id": 2348,
          "profile_image": "https://spacelaunchnow-prod-east.nyc3.digitaloceanspaces.com/media/profile_images/arnaud2520muller_profile_20230607144351.jpg",
          "comment": "Adjusting T-0",
          "info_url": "http://www.launchphotography.com/Launch_Viewing_Guide.html",
          "created_by": "Nosu",
          "created_on": "2022-09-07T21:14:29Z"
        },
        {
          "id": 2342,
          "profile_image": "https://spacelaunchnow-prod-east.nyc3.digitaloceanspaces.com/media/profile_images/arnaud2520muller_profile_20230607144351.jpg",
          "comment": "Setting TBC",
          "info_url": "https://spaceflightnow.com/launch-schedule/",
          "created_by": "Nosu",
          "created_on": "2022-09-06T20:24:19Z"
        },
        {
          "id": 2312,
          "profile_image": "https://spacelaunchnow-prod-east.nyc3.digitaloceanspaces.com/media/profile_images/arnaud2520muller_profile_20230607144351.jpg",
          "comment": "NET September 12",
          "info_url": "https://spaceflightnow.com/launch-schedule/",
          "created_by": "Nosu",
          "created_on": "2022-09-01T07:03:47Z"
        },
        {
          "id": 2211,
          "profile_image": "https://spacelaunchnow-prod-east.nyc3.digitaloceanspaces.com/media/profile_images/arnaud2520muller_profile_20230607144351.jpg",
          "comment": "Adding launch NET September",
          "info_url": "https://apps.fcc.gov/oetcf/els/reports/STA_Print.cfm?mode=current&application_seq=117603",
          "created_by": "Nosu",
          "created_on": "2022-08-10T08:44:40Z"
        }
      ],
      "net": "2022-09-19T00:18:00Z",
      "net_precision": null,
      "window_end": "2022-09-19T00:18:00Z",
      "window_start": "2022-09-19T00:18:00Z",
      "probability": 80,
      "weather_concerns": null,
      "holdreason": "",
      "failreason": "",
      "hashtag": null,
      "launch_service_provider": {
        "id": 121,
        "url": "https://ll.thespacedevs.com/2.2.0/agencies/121/?format=json",
        "name": "SpaceX",
        "featured": true,
        "type": "Commercial",
        "country_code": "USA",
        "abbrev": "SpX",
        "description": "Space Exploration Technologies Corp., known as SpaceX, is an American aerospace manufacturer and space transport services company headquartered in Hawthorne, California. It was founded in 2002 by entrepreneur Elon Musk with the goal of reducing space transportation costs and enabling the colonization of Mars. SpaceX operates from many pads, on the East Coast of the US they operate from SLC-40 at Cape Canaveral Space Force Station and historic LC-39A at Kennedy Space Center. They also operate from SLC-4E at Vandenberg Space Force Base, California, usually for polar launches. Another launch site is being developed at Boca Chica, Texas.",
        "administrator": "CEO: Elon Musk",
        "founding_year": "2002",
        "launchers": "Falcon | Starship",
        "spacecraft": "Dragon",
        "launch_library_url": "https://launchlibrary.net/1.4/agency/121",
        "total_launch_count": 281,
        "consecutive_successful_launches": 42,
        "successful_launches": 271,
        "failed_launches": 10,
        "pending_launches": 134,
        "consecutive_successful_landings": 151,
        "successful_landings": 233,
        "failed_landings": 22,
        "attempted_landings": 254,
        "info_url": "http://www.spacex.com/",
        "wiki_url": "http://en.wikipedia.org/wiki/SpaceX",
        "logo_url": "https://spacelaunchnow-prod-east.nyc3.digitaloceanspaces.com/media/logo/spacex_logo_20220826094919.png",
        "image_url": "https://spacelaunchnow-prod-east.nyc3.digitaloceanspaces.com/media/agency_images/spacex_image_20190207032501.jpeg",
        "nation_url": "https://spacelaunchnow-prod-east.nyc3.digitaloceanspaces.com/media/agency_nation/spacex_nation_20230531064544.jpg"
      },
      "rocket": {
        "id": 7623,
        "configuration": {
          "id": 164,
          "url": "https://ll.thespacedevs.com/2.2.0/config/launcher/164/?format=json",
          "name": "Falcon 9",
          "active": true,
          "reusable": true,
          "description": "Falcon 9 is a two-stage rocket designed and manufactured by SpaceX for the reliable and safe transport of satellites and the Dragon spacecraft into orbit. The Block 5 variant is the fifth major interval aimed at improving upon the ability for rapid reusability.",
          "family": "Falcon",
          "full_name": "Falcon 9 Block 5",
          "manufacturer": {
            "id": 121,
            "url": "https://ll.thespacedevs.com/2.2.0/agencies/121/?format=json",
            "name": "SpaceX",
            "featured": true,
            "type": "Commercial",
            "country_code": "USA",
            "abbrev": "SpX",
            "description": "Space Exploration Technologies Corp., known as SpaceX, is an American aerospace manufacturer and space transport services company headquartered in Hawthorne, California. It was founded in 2002 by entrepreneur Elon Musk with the goal of reducing space transportation costs and enabling the colonization of Mars. SpaceX operates from many pads, on the East Coast of the US they operate from SLC-40 at Cape Canaveral Space Force Station and historic LC-39A at Kennedy Space Center. They also operate from SLC-4E at Vandenberg Space Force Base, California, usually for polar launches. Another launch site is being developed at Boca Chica, Texas.",
            "administrator": "CEO: Elon Musk",
            "founding_year": "2002",
            "launchers": "Falcon | Starship",
            "spacecraft": "Dragon",
            "launch_library_url": "https://launchlibrary.net/1.4/agency/121",
            "total_launch_count": 281,
            "consecutive_successful_launches": 42,
            "successful_launches": 271,
            "failed_launches": 10,
            "pending_launches": 134,
            "consecutive_successful_landings": 151,
            "successful_landings": 233,
            "failed_landings": 22,
            "attempted_landings": 254,
            "info_url": "http://www.spacex.com/",
            "wiki_url": "http://en.wikipedia.org/wiki/SpaceX",
            "logo_url": "https://spacelaunchnow-prod-east.nyc3.digitaloceanspaces.com/media/logo/spacex_logo_20220826094919.png",
            "image_url": "https://spacelaunchnow-prod-east.nyc3.digitaloceanspaces.com/media/agency_images/spacex_image_20190207032501.jpeg",
            "nation_url": "https://spacelaunchnow-prod-east.nyc3.digitaloceanspaces.com/media/agency_nation/spacex_nation_20230531064544.jpg"
          },
          "program": [
            {
              "id": 5,
              "url": "https://ll.thespacedevs.com/2.2.0/program/5/?format=json",
              "name": "Commercial Crew Program",
              "description": "The Commercial Crew Program (CCP) is a human spaceflight program operated by NASA, in association with American aerospace manufacturers Boeing and SpaceX. The program conducts rotations between the expeditions of the International Space Station program, transporting crews to and from the International Space Station (ISS) aboard Boeing Starliner and SpaceX Crew Dragon capsules, in the first crewed orbital spaceflights operated by private companies.",
              "agencies": [
                {
                  "id": 80,
                  "url": "https://ll.thespacedevs.com/2.2.0/agencies/80/?format=json",
                  "name": "Boeing",
                  "type": "Commercial"
                },
                {
                  "id": 44,
                  "url": "https://ll.thespacedevs.com/2.2.0/agencies/44/?format=json",
                  "name": "National Aeronautics and Space Administration",
                  "type": "Government"
                },
                {
                  "id": 121,
                  "url": "https://ll.thespacedevs.com/2.2.0/agencies/121/?format=json",
                  "name": "SpaceX",
                  "type": "Commercial"
                }
              ],
              "image_url": "https://spacelaunchnow-prod-east.nyc3.digitaloceanspaces.com/media/program_images/commercial2520_program_20200820201209.png",
              "start_date": "2011-04-18T00:00:00Z",
              "end_date": null,
              "info_url": "https://www.nasa.gov/exploration/commercial/crew/index.html",
              "wiki_url": "https://en.wikipedia.org/wiki/Commercial_Crew_Program",
              "mission_patches": []
            },
            {
              "id": 11,
              "url": "https://ll.thespacedevs.com/2.2.0/program/11/?format=json",
              "name": "Commercial Resupply Services",
              "description": "Commercial Resupply Services (CRS) are a series of flights awarded by NASA for the delivery of cargo and supplies to the International Space Station.The first CRS contracts were signed in 2008 and awarded $1.6 billion to SpaceX for twelve cargo Dragon and $1.9 billion to Orbital Sciences for eight Cygnus flights, covering deliveries to 2016. The Falcon 9 and Antares rockets were also developed under the CRS program to deliver cargo spacecraft to the ISS.",
              "agencies": [
                {
                  "id": 44,
                  "url": "https://ll.thespacedevs.com/2.2.0/agencies/44/?format=json",
                  "name": "National Aeronautics and Space Administration",
                  "type": "Government"
                },
                {
                  "id": 257,
                  "url": "https://ll.thespacedevs.com/2.2.0/agencies/257/?format=json",
                  "name": "Northrop Grumman Space Systems",
                  "type": "Commercial"
                },
                {
                  "id": 1020,
                  "url": "https://ll.thespacedevs.com/2.2.0/agencies/1020/?format=json",
                  "name": "Sierra Nevada Corporation",
                  "type": "Commercial"
                },
                {
                  "id": 121,
                  "url": "https://ll.thespacedevs.com/2.2.0/agencies/121/?format=json",
                  "name": "SpaceX",
                  "type": "Commercial"
                }
              ],
              "image_url": "https://spacelaunchnow-prod-east.nyc3.digitaloceanspaces.com/media/program_images/commercial2520_program_20201129212219.png",
              "start_date": "2008-12-23T00:00:00Z",
              "end_date": null,
              "info_url": null,
              "wiki_url": "https://en.wikipedia.org/wiki/Commercial_Resupply_Services#Commercial_Resupply_Services",
              "mission_patches": []
            }
          ],
          "variant": "Block 5",
          "alias": "",
          "min_stage": 1,
          "max_stage": 2,
          "length": 70,
          "diameter": 3.65,
          "maiden_flight": "2018-05-11",
          "launch_cost": "52000000",
          "launch_mass": 549,
          "leo_capacity": 22800,
          "gto_capacity": 8300,
          "to_thrust": 7607,
          "apogee": 200,
          "vehicle_range": null,
          "image_url": "https://spacelaunchnow-prod-east.nyc3.digitaloceanspaces.com/media/launcher_images/falcon_9_image_20230807133459.jpeg",
          "info_url": "https://www.spacex.com/vehicles/falcon-9/",
          "wiki_url": "https://en.wikipedia.org/wiki/Falcon_9",
          "total_launch_count": 202,
          "consecutive_successful_launches": 202,
          "successful_launches": 202,
          "failed_launches": 0,
          "pending_launches": 123,
          "attempted_landings": 197,
          "successful_landings": 193,
          "failed_landings": 4,
          "consecutive_successful_landings": 148
        },
        "launcher_stage": [
          {
            "id": 269,
            "type": "Core",
            "reused": true,
            "launcher_flight_number": 6,
            "launcher": {
              "id": 101,
              "url": "https://ll.thespacedevs.com/2.2.0/launcher/101/?format=json",
              "details": "Falcon 9 Block 5 booster first used for the CRS-22 mission.",
              "flight_proven": true,
              "serial_number": "B1067",
              "status": "active",
              "image_url": "https://spacelaunchnow-prod-east.nyc3.digitaloceanspaces.com/media/launcher_core_images/101_image_20210602203045.jpeg",
              "successful_landings": 13,
              "attempted_landings": 13,
              "flights": 13,
              "last_launch_date": "2023-08-17T03:36:50Z",
              "first_launch_date": "2021-06-03T17:29:15Z"
            },
            "landing": {
              "id": 297,
              "attempt": true,
              "success": true,
              "description": "B1067 has successfully landed on ASDS JRTI after its 6th launch.",
              "downrange_distance": 666,
              "location": {
                "id": 3,
                "name": "Just Read the Instructions",
                "abbrev": "JRTI",
                "description": "First (Marmac 300) and third (Marmac 303) ASDS barge, Just Read the Instructions (JRTI) is currently used to recover Falcon 9 and Heavy boosters in the Altantic Ocean.",
                "location": null,
                "successful_landings": 63
              },
              "type": {
                "id": 1,
                "name": "Autonomous Spaceport Drone Ship",
                "abbrev": "ASDS",
                "description": "An autonomous spaceport drone ship (ASDS) is an ocean-going vessel derived from a deck barge, outfitted with station-keeping engines and a large landing platform. Construction of such ships was commissioned by aerospace company SpaceX to allow for recovery of rocket first-stages at sea for high-velocity missions which do not carry enough fuel to return to the launch site after lofting spacecraft onto an orbital trajectory."
              }
            },
            "previous_flight_date": "2022-07-15T00:44:20Z",
            "turn_around_time_days": 65,
            "previous_flight": {
              "id": "2773613e-58eb-4b99-8120-595c92aa3390",
              "name": "Falcon 9 Block 5 | Dragon CRS-2 SpX-25"
            }
          }
        ],
        "spacecraft_stage": null
      },
      "mission": {
        "id": 6123,
        "name": "Starlink Group 4-34",
        "description": "A batch of 54 satellites for Starlink mega-constellation - SpaceX's project for space-based Internet communication system.",
        "launch_designator": null,
        "type": "Communications",
        "orbit": {
          "id": 8,
          "name": "Low Earth Orbit",
          "abbrev": "LEO"
        },
        "agencies": [],
        "info_urls": [],
        "vid_urls": []
      },
      "pad": {
        "id": 80,
        "url": "https://ll.thespacedevs.com/2.2.0/pad/80/?format=json",
        "agency_id": 121,
        "name": "Space Launch Complex 40",
        "description": null,
        "info_url": null,
        "wiki_url": "https://en.wikipedia.org/wiki/Cape_Canaveral_Air_Force_Station_Space_Launch_Complex_40",
        "map_url": "https://www.google.com/maps?q=28.56194122,-80.57735736",
        "latitude": "28.56194122",
        "longitude": "-80.57735736",
        "location": {
          "id": 12,
          "url": "https://ll.thespacedevs.com/2.2.0/location/12/?format=json",
          "name": "Cape Canaveral, FL, USA",
          "country_code": "USA",
          "description": null,
          "map_image": "https://spacelaunchnow-prod-east.nyc3.digitaloceanspaces.com/media/launch_images/location_12_20200803142519.jpg",
          "timezone_name": "America/New_York",
          "total_launch_count": 909,
          "total_landing_count": 37
        },
        "country_code": "USA",
        "map_image": "https://spacelaunchnow-prod-east.nyc3.digitaloceanspaces.com/media/launch_images/pad_80_20200803143323.jpg",
        "total_launch_count": 201,
        "orbital_launch_attempt_count": 201
      },
      "infoURLs": [
        {
          "priority": 10,
          "source": null,
          "title": "SpaceX",
          "description": "SpaceX designs, manufactures and launches advanced rockets and spacecraft. The company was founded in 2002 to revolutionize space technology, with the ultimate goal of enabling people to live on other planets.",
          "feature_image": null,
          "url": "https://www.spacex.com/launches/sl4-34/",
          "type": null,
          "language": null
        }
      ],
      "vidURLs": [
        {
          "priority": 9,
          "source": null,
          "title": "Starlink Mission",
          "description": "SpaceX is targeting Saturday, September 17 for a Falcon 9 launch of 54 Starlink satellites to low-Earth orbit from Space Launch Complex 40 (SLC-40) at Cape C...",
          "feature_image": "https://i.ytimg.com/vi/ZlQHF_yBkMQ/maxresdefault_live.jpg",
          "url": "https://youtube.com/watch?v=ZlQHF_yBkMQ",
          "type": null,
          "language": null
        },
        {
          "priority": 10,
          "source": null,
          "title": "Starlink Mission",
          "description": "SpaceX is targeting Saturday, September 17 for a Falcon 9 launch of 54 Starlink satellites to low-Earth orbit from Space Launch Complex 40 (SLC-40) at Cape C...",
          "feature_image": "https://i.ytimg.com/vi/ZlQHF_yBkMQ/maxresdefault_live.jpg",
          "url": "https://www.youtube.com/watch?v=ZlQHF_yBkMQ",
          "type": null,
          "language": null
        },
        {
          "priority": 11,
          "source": null,
          "title": "Starlink Mission",
          "description": "SpaceX is targeting Friday, September 16 for a Falcon 9 launch of 54 Starlink satellites to low-Earth orbit from Space Launch Complex 40 (SLC-40) at Cape Can...",
          "feature_image": "https://i.ytimg.com/vi/f3TWiIjDVSs/maxresdefault.jpg",
          "url": "https://www.youtube.com/watch?v=f3TWiIjDVSs",
          "type": null,
          "language": null
        },
        {
          "priority": 12,
          "source": null,
          "title": "Starlink Mission",
          "description": "SpaceX is targeting Thursday, September 15 for a Falcon 9 launch of 54 Starlink satellites to low-Earth orbit from Space Launch Complex 40 (SLC-40) at Cape C...",
          "feature_image": "https://i.ytimg.com/vi/JzWSYJBSAl4/hqdefault.jpg",
          "url": "https://www.youtube.com/watch?v=JzWSYJBSAl4",
          "type": null,
          "language": null
        }
      ],
      "webcast_live": false,
      "image": "https://spacelaunchnow-prod-east.nyc3.digitaloceanspaces.com/media/launch_images/falcon2520925_image_20220810084439.png",
      "infographic": null,
      "program": [],
      "orbital_launch_attempt_count": 6289,
      "location_launch_attempt_count": 857,
      "pad_launch_attempt_count": 153,
      "agency_launch_attempt_count": 194,
      "orbital_launch_attempt_count_year": 118,
      "location_launch_attempt_count_year": 27,
      "pad_launch_attempt_count_year": 20,
      "agency_launch_attempt_count_year": 42,
      "pad_turnaround": "P13DT22H8M20S",
      "mission_patches": [
        {
          "id": 7,
          "name": "Space X Starlink Mission Patch",
          "priority": 10,
          "image_url": "https://spacelaunchnow-prod-east.nyc3.digitaloceanspaces.com/media/mission_patch_images/space2520x252_mission_patch_20221011205756.png",
          "agency": {
            "id": 121,
            "url": "https://ll.thespacedevs.com/2.2.0/agencies/121/?format=json",
            "name": "SpaceX",
            "type": "Commercial"
          }
        }
      ]
    }
  ]
}